<?xml version="1.0" encoding="utf-8"?>
<resources>
    <!-- 各画面タイトル -->
    <string name="title_ui0002">ログイン</string>
    <string name="title_ui0003">利用規定同意</string>
    <string name="title_ui0004">ワンタイム認証</string>
    <string name="title_ui0005">ワンタイムキー発行</string>
    <string name="title_ui0006">生年月日認証</string>
    <string name="title_ui0007">クイック登録完了</string>
    <string name="title_ui0008">クイックログイン</string>
    <string name="title_ui0010">ヘルプ</string>
    <string name="title_ui0011">お知らせ</string>
    <string name="title_ui0012">メインメニュー</string>
    <string name="title_ui0013">My Account</string>
    <string name="title_ui0014">入出金照会</string>
    <string name="title_ui0015">詳細</string>
    <string name="title_ui0016">通帳</string>
    <string name="title_ui0017">受取人選択方法</string>
    <string name="title_ui0018a">アドレス帳一覧</string>
    <string name="title_ui0018b">端末の連絡先一覧</string>
    <string name="title_ui0019">振込内容入力</string>
    <string name="title_ui0020">振込内容確認</string>
    <string name="title_ui0021">振込完了</string>
    <string name="title_ui0022">設定</string>
    <string name="title_ui0023a">振込内容登録</string>
    <string name="title_ui0023b">振込内容選択</string>
    <string name="title_ui0024">通帳の柄選択</string>
    <string name="title_ui0025">ログアウト</string>
    <string name="title_ui0031">チュートリアル</string>
    <string name="title_ui0032">チュートリアル</string>
    <string name="title_ui0033">チュートリアル</string>
    <string name="title_ui0040">ユーザID設定：登録</string>
    <string name="title_ui0041">ユーザID設定：完了</string>
    <string name="title_ui0042">ログインパスワード設定：登録</string>
    <string name="title_ui0043">暗証番号設定</string>
    <string name="title_ui0070">ユーザID・ログインパスワードがご不明なお客さま</string>
    <string name="title_ui0071">ユーザID初期化</string>
    <string name="title_ui0072">ユーザID初期化：実行</string>
    <string name="title_ui0073">ユーザID初期化：完了</string>
    <string name="title_ui0074">ログインパスワードが不明な場合</string>
    <string name="title_ui0075">ログインパスワード設定用番号発行</string>
    <string name="title_ui0076">ログインパスワード設定用番号発行</string>
    <string name="title_ui0077">再ログイン</string>
    <string name="title_ui0100">振込トップ</string>
    <string name="title_ui0101">金融機関選択</string>
    <string name="title_ui0102">金融機関選択(銀行検索)</string>
    <string name="title_ui0103">支店選択</string>
    <string name="title_ui0104">支店選択</string>
    <string name="title_ui0105">登録済みの振込先口座一覧</string>
    <string name="title_ui0106">振込先口座の確認</string>
    <string name="title_ui0107">振込先口座の削除</string>
    <string name="title_ui0108">削除完了</string>
    <string name="title_ui0110">振込メニュー</string>
    <string name="title_ui0111">振込情報入力</string>
    <string name="title_ui0112">振込情報入力</string>
    <string name="title_ui0113">振込内容の確認</string>
    <string name="title_ui0114">振込完了</string>
    <string name="title_ui0115">振込情報入力</string>
    <string name="title_ui0116">振込情報入力</string>
    <string name="title_ui0117">振込情報入力</string>
    <string name="title_ui0118">振込内容の確認</string>
    <string name="title_ui0119">振込完了</string>
    <string name="title_ui0120">振込手数料のポイント支払</string>
    <string name="title_ui0121">毎月おまかせ振込予約</string>
    <string name="title_ui0122">振込情報入力</string>
    <string name="title_ui0123">振込内容の確認</string>
    <string name="title_ui0124">振込完了</string>
    <string name="title_ui0125">毎月おまかせ振込予約一覧</string>
    <string name="title_ui0126">設定内容の確認・削除</string>
    <string name="title_ui0127">振込予約削除完了</string>
    <string name="title_ui0130">振込予約一覧</string>
    <string name="title_ui0131">振込予約の取消</string>
    <string name="title_ui0132">振込予約 取消完了</string>
    <string name="title_ui0140">セキュリティカード認証</string>
    <string name="title_ui0141">ご本人確認</string>
    <string name="title_ui0142">チュートリアル</string>
    <string name="title_ui0150">ワンタイム認証に利用する\nメールアドレスの設定</string>
    <string name="title_ui_lottery">宝くじ</string>
    <string name="title_ui_lottery_normal">通常購入</string>
    <string name="title_ui_lottery_auto">自動購入設定</string>
    <string name="title_ui_lottery_simple">かんたん購入</string>
    <string name="title_ui_lottery_history">購入履歴・\n当せん結果履歴</string>
    <string name="title_ui_lottery_history_auto">自動購入設定</string>
    <string name="title_ui0170">背景設定</string>
    <string name="title_ui0171">背景設定</string>
    <string name="title_ui0250">外貨普通預金</string>
    <string name="title_ui0251">{0}のお取引状況</string>
    <string name="title_ui0252">入出金明細</string>
    <string name="title_ui0253">お知らせ</string>
    <string name="title_ui0270">お預入金額の入力</string>
    <string name="title_ui0271">お預入内容の確認</string>
    <string name="title_ui0272">お預入完了</string>
    <string name="title_ui0273">お預入できません</string>
    <string name="title_ui0275">お払戻金額の入力</string>
    <string name="title_ui0276">お払戻内容の確認</string>
    <string name="title_ui0277">お払戻完了</string>
    <string name="title_ui0280">金利一覧</string>
    <string name="title_ui0300">{0}</string>
    <string name="title_ui0301">{0}口座開設</string>
    <string name="title_ui0302">{0}口座開設</string>
    <string name="title_ui0303">{0}口座開設</string>
    <string name="title_ui0304">{0}口座開設</string>
    <string name="title_ui0305">{0}口座開設</string>
    <string name="title_ui0306">{0}口座開設</string>
    <string name="title_ui0307">{0}口座開設</string>
    <string name="title_ui0308">{0}</string>
    <string name="title_ui0330">{0}口座開設</string>
    <string name="title_ui0331">申込受付完了</string>
    <string name="title_ui0335">レバレッジコースの選択</string>
    <string name="title_ui0310">メール設定</string>
    <string name="title_ui0315">FX口座に振替</string>
    <string name="title_ui0316">FX口座に振替</string>
    <string name="title_ui0317">FX口座に振替</string>
    <string name="title_ui0320">円普通預金口座に振替</string>
    <string name="title_ui0321">円普通預金口座に振替</string>
    <string name="title_ui0322">円普通預金口座に振替</string>
    <string name="title_ui0325">{0}口座の解約</string>
    <string name="title_ui0326">{0}口座の解約</string>
    <string name="title_ui0400">お客様カードの入力</string>
    <string name="title_ui0401">お客様カードの確認</string>
    <string name="title_ui0608">ATM・コンビニ</string>
    <string name="title_ui0609">金利一覧</string>
    <string name="title_ui0610">住宅ローン</string>
    <string name="title_ui0611">カードローン</string>
    <string name="title_ui0612">ヘルプ</string>
    <string name="title_ui0613">ATM・コンビニ</string>
</resources>
